Metadata-Version: 2.1
Name: xtbf
Version: 0.1.3
Summary: A minimal, functional interface to the semiempirical extended tight-binding (xtb) program
Home-page: https://github.com/Bayer-Group/xtbf
Author: Jan Wollschläger
Author-email: janmwoll@gmail.com
License: BSD 3-clause
Classifier: Intended Audience :: Science/Research
Classifier: License :: OSI Approved :: BSD License
Classifier: Programming Language :: Python :: 3
License-File: LICENSE
Requires-Dist: joblib
Requires-Dist: tqdm
Requires-Dist: numpy
Requires-Dist: pandas
